minimax/__init__.py
minimax/arguments.py
minimax/evaluate.py
minimax/train.py
minimax/agents/__init__.py
minimax/agents/agent.py
minimax/agents/ppo.py
minimax/config/__init__.py
minimax/config/make_cmd.py
minimax/config/xpid_maker.py
minimax/config/configs/maze/accel.json
minimax/config/configs/maze/dr.json
minimax/config/configs/maze/paccel.json
minimax/config/configs/maze/paired.json
minimax/config/configs/maze/plr.json
minimax/config/configs/maze/pplr.json
minimax/config/configs/maze/s5_accel.json
minimax/config/configs/maze/s5_dr.json
minimax/config/configs/maze/s5_paccel.json
minimax/config/configs/maze/s5_paired.json
minimax/config/configs/maze/s5_plr.json
minimax/config/configs/maze/s5_pplr.json
minimax/envs/__init__.py
minimax/envs/batch_env.py
minimax/envs/batch_env_ued.py
minimax/envs/environment.py
minimax/envs/environment_ued.py
minimax/envs/registration.py
minimax/envs/spaces.py
minimax/envs/interactive/__init__.py
minimax/envs/interactive/manual_ctrl_maze.py
minimax/envs/maze/__init__.py
minimax/envs/maze/common.py
minimax/envs/maze/maze.py
minimax/envs/maze/maze_comparators.py
minimax/envs/maze/maze_mutators.py
minimax/envs/maze/maze_ood.py
minimax/envs/maze/maze_ued.py
minimax/envs/viz/__init__.py
minimax/envs/viz/grid_rendering.py
minimax/envs/viz/grid_viz.py
minimax/envs/viz/window.py
minimax/envs/wrappers/__init__.py
minimax/envs/wrappers/env_wrapper.py
minimax/envs/wrappers/monitor_ep_metrics.py
minimax/envs/wrappers/monitor_return.py
minimax/envs/wrappers/ued_env_wrapper.py
minimax/models/__init__.py
minimax/models/common.py
minimax/models/registration.py
minimax/models/rnn.py
minimax/models/s5.py
minimax/models/maze/__init__.py
minimax/models/maze/gridworld_models.py
minimax/runners/__init__.py
minimax/runners/dr_runner.py
minimax/runners/eval_runner.py
minimax/runners/paired_runner.py
minimax/runners/plr_runner.py
minimax/runners/xp_runner.py
minimax/tests/__init__.py
minimax/tests/base_req_rollout_storage.py
minimax/tests/dummy_test_envs.py
ued-0.2.0.dist-info/LICENSE
ued-0.2.0.dist-info/METADATA
ued-0.2.0.dist-info/WHEEL
ued-0.2.0.dist-info/top_level.txt
ued-0.2.0.dist-info/RECORD
